{
  "name": "puppet-ssh_keygen",
  "version": "3.0.0",
  "author": "Vox Pupuli",
  "summary": "Generate ssh keys with ssh_keygen",
  "license": "Apache-2.0",
  "source": "http://github.com/voxpupuli/puppet-ssh_keygen.git",
  "description": "Generate ssh keys for any user using ssh_keygen, that needs to be present before using the module",
  "project_page": "http://github.com/voxpupuli/puppet-ssh_keygen",
  "requirements": [
    {
      "name": "puppet",
      "version_requirement": ">= 4.10.0 < 6.0.0"
    }
  ],
  "dependencies": [
    {
      "name": "puppet-stdlib",
      "version_requirement": ">= 4.13.0 < 5.0.0"
    }
  ]
}
